README.md
setup.py
pulumiverse_heroku/__init__.py
pulumiverse_heroku/_inputs.py
pulumiverse_heroku/_utilities.py
pulumiverse_heroku/provider.py
pulumiverse_heroku/pulumi-plugin.json
pulumiverse_heroku/py.typed
pulumiverse_heroku.egg-info/PKG-INFO
pulumiverse_heroku.egg-info/SOURCES.txt
pulumiverse_heroku.egg-info/dependency_links.txt
pulumiverse_heroku.egg-info/not-zip-safe
pulumiverse_heroku.egg-info/requires.txt
pulumiverse_heroku.egg-info/top_level.txt
pulumiverse_heroku/account/__init__.py
pulumiverse_heroku/account/feature.py
pulumiverse_heroku/addon/__init__.py
pulumiverse_heroku/addon/addon.py
pulumiverse_heroku/addon/attachment.py
pulumiverse_heroku/addon/get_addon.py
pulumiverse_heroku/app/__init__.py
pulumiverse_heroku/app/_inputs.py
pulumiverse_heroku/app/app.py
pulumiverse_heroku/app/config.py
pulumiverse_heroku/app/config_association.py
pulumiverse_heroku/app/feature.py
pulumiverse_heroku/app/get_app.py
pulumiverse_heroku/app/outputs.py
pulumiverse_heroku/app/release.py
pulumiverse_heroku/app/webhook.py
pulumiverse_heroku/build/__init__.py
pulumiverse_heroku/build/_inputs.py
pulumiverse_heroku/build/build.py
pulumiverse_heroku/build/outputs.py
pulumiverse_heroku/cert/__init__.py
pulumiverse_heroku/cert/cert.py
pulumiverse_heroku/collaborator/__init__.py
pulumiverse_heroku/collaborator/collaborator.py
pulumiverse_heroku/config/__init__.py
pulumiverse_heroku/config/config.py
pulumiverse_heroku/config/outputs.py
pulumiverse_heroku/config/vars.py
pulumiverse_heroku/domain/__init__.py
pulumiverse_heroku/domain/domain.py
pulumiverse_heroku/drain/__init__.py
pulumiverse_heroku/drain/drain.py
pulumiverse_heroku/formation/__init__.py
pulumiverse_heroku/formation/formation.py
pulumiverse_heroku/pipeline/__init__.py
pulumiverse_heroku/pipeline/_inputs.py
pulumiverse_heroku/pipeline/config_var.py
pulumiverse_heroku/pipeline/coupling.py
pulumiverse_heroku/pipeline/get_pipeline.py
pulumiverse_heroku/pipeline/outputs.py
pulumiverse_heroku/pipeline/pipeline.py
pulumiverse_heroku/review/__init__.py
pulumiverse_heroku/review/_inputs.py
pulumiverse_heroku/review/app_config.py
pulumiverse_heroku/review/outputs.py
pulumiverse_heroku/slug/__init__.py
pulumiverse_heroku/slug/_inputs.py
pulumiverse_heroku/slug/outputs.py
