Metadata-Version: 2.1
Name: pulumiverse-heroku
Version: 1.0.3
Summary: A Pulumi package for creating and managing heroku cloud resources.
Home-page: https://www.pulumi.com
License: Apache-2.0
Project-URL: Repository, https://github.com/pulumiverse/pulumi-heroku
Keywords: pulumi heroku category/cloud
Platform: UNKNOWN
